[
  {
    "experiment": "lstm",
    "results": {
      "1": {
        "false": 13.18074893951416,
        "true": 12.735315322875977
      },
      "2": {
        "false": 12.871631622314453,
        "true": 13.332671165466309
      },
      "3": {
        "false": 12.607126235961914,
        "true": 14.35992431640625
      },
      "4": {
        "false": 12.686575889587402,
        "true": 13.371859550476074
      },
      "5": {
        "false": 12.834678649902344,
        "true": 12.954070091247559
      },
      "6": {
        "false": 12.78524398803711,
        "true": 13.229573249816895
      },
      "7": {
        "false": 12.768755912780762,
        "true": 13.3150053024292
      },
      "8": {
        "false": 12.745438575744629,
        "true": 14.345196723937988
      },
      "9": {
        "false": 13.215361595153809,
        "true": 13.266271591186523
      },
      "10": {
        "false": 13.221923828125,
        "true": 14.352059364318848
      },
      "11": {
        "false": 13.243953704833984,
        "true": 14.021114349365234
      },
      "12": {
        "false": 13.263957023620605,
        "true": 14.276569366455078
      },
      "13": {
        "false": 13.495217323303223,
        "true": 13.509038925170898
      },
      "14": {
        "false": 13.37135124206543,
        "true": 13.343133926391602
      },
      "21": {
        "false": 13.303936958312988,
        "true": 14.452640533447266
      },
      "28": {
        "false": 13.967352867126465,
        "true": 15.448465347290039
      },
      "35": {
        "false": 13.745281219482422,
        "true": 15.483778953552246
      },
      "42": {
        "false": 13.75720500946045,
        "true": 14.293606758117676
      },
      "49": {
        "false": 13.957277297973633,
        "true": 15.315159797668457
      },
      "56": {
        "false": 13.828603744506836,
        "true": 15.212726593017578
      },
      "63": {
        "false": 14.57319450378418,
        "true": 16.044132232666016
      },
      "70": {
        "false": 14.300625801086426,
        "true": 14.289037704467773
      },
      "77": {
        "false": 14.283317565917969,
        "true": 14.632867813110352
      },
      "84": {
        "false": 14.429261207580566,
        "true": 14.692156791687012
      },
      "91": {
        "false": 14.68606948852539,
        "true": 15.65431022644043
      },
      "98": {
        "false": 14.898688316345215,
        "true": 16.158706665039062
      },
      "105": {
        "false": 14.894065856933594,
        "true": 15.479475021362305
      },
      "112": {
        "false": 15.412381172180176,
        "true": 17.0760498046875
      },
      "119": {
        "false": 15.990493774414062,
        "true": 16.02389907836914
      },
      "126": {
        "false": 15.744444847106934,
        "true": 17.133407592773438
      },
      "133": {
        "false": 16.108688354492188,
        "true": 15.87328052520752
      },
      "140": {
        "false": 16.432415008544922,
        "true": 18.187808990478516
      },
      "147": {
        "false": 17.000301361083984,
        "true": 15.909212112426758
      },
      "154": {
        "false": 16.45925521850586,
        "true": 15.221659660339355
      }
    }
  },
  {
    "experiment": "lstm",
    "results": {
      "1": {
        "true": 12.940398216247559
      },
      "2": {
        "true": 12.935916900634766
      },
      "3": {
        "true": 12.616802215576172
      },
      "4": {
        "true": 13.560646057128906
      },
      "5": {
        "true": 14.105093955993652
      },
      "6": {
        "true": 13.77155590057373
      },
      "7": {
        "true": 14.809416770935059
      },
      "8": {
        "true": 13.541153907775879
      },
      "9": {
        "true": 14.406672477722168
      },
      "10": {
        "true": 15.000936508178711
      },
      "11": {
        "true": 15.301010131835938
      },
      "12": {
        "true": 15.257601737976074
      },
      "13": {
        "true": 16.38508415222168
      },
      "14": {
        "true": 44.87196731567383
      },
      "21": {
        "true": 44.0811767578125
      },
      "28": {
        "true": 30.332351684570312
      },
      "35": {
        "true": 45.97720718383789
      },
      "42": {
        "true": 47.49400329589844
      },
      "49": {
        "true": 41.07514572143555
      },
      "56": {
        "true": Infinity
      }
    }
  },
  {
    "experiment": "lstm",
    "results": {
      "1": {
        "false": 12.58582592010498,
        "true": 14.727259635925293
      }
    }
  },
  {
    "experiment": "lstm",
    "results": {
      "1": {
        "false": 12.792387962341309,
        "true": 12.882670402526855
      },
      "2": {
        "false": 12.857771873474121,
        "true": 13.863856315612793
      },
      "3": {
        "false": 12.56701946258545,
        "true": 12.67026138305664
      },
      "4": {
        "false": 12.398748397827148,
        "true": 12.589082717895508
      },
      "5": {
        "false": 12.421202659606934,
        "true": 12.804399490356445
      },
      "6": {
        "false": 12.396238327026367,
        "true": 12.283172607421875
      },
      "7": {
        "false": 12.310935974121094,
        "true": 12.47226333618164
      },
      "8": {
        "false": 12.654430389404297,
        "true": 12.814362525939941
      },
      "9": {
        "false": 12.588848114013672,
        "true": 12.71646785736084
      },
      "10": {
        "false": 12.757593154907227,
        "true": 13.02479076385498
      },
      "11": {
        "false": 12.740562438964844,
        "true": 13.149116516113281
      },
      "12": {
        "false": 12.908113479614258,
        "true": 13.06915283203125
      },
      "13": {
        "false": 12.814187049865723,
        "true": 13.019903182983398
      },
      "14": {
        "false": 13.040144920349121,
        "true": 12.897787094116211
      },
      "21": {
        "false": 12.863004684448242,
        "true": 13.210609436035156
      },
      "28": {
        "false": 13.172444343566895,
        "true": 13.41679859161377
      },
      "35": {
        "false": 14.05477237701416,
        "true": 14.544422149658203
      },
      "42": {
        "false": 13.494050025939941,
        "true": 14.836700439453125
      },
      "49": {
        "false": 15.013616561889648,
        "true": 16.0712833404541
      },
      "56": {
        "false": 13.624658584594727,
        "true": 15.171278953552246
      },
      "63": {
        "false": 16.108051300048828,
        "true": 16.392854690551758
      },
      "70": {
        "false": 15.29178237915039,
        "true": 15.686845779418945
      },
      "77": {
        "false": 15.484206199645996,
        "true": 16.17053985595703
      },
      "84": {
        "false": 16.865550994873047,
        "true": 15.929443359375
      },
      "91": {
        "false": 15.963348388671875,
        "true": 16.76638412475586
      },
      "98": {
        "false": 16.216955184936523,
        "true": 17.14964485168457
      },
      "105": {
        "false": 16.979965209960938,
        "true": 18.750320434570312
      },
      "112": {
        "false": 18.479480743408203,
        "true": 18.47208023071289
      },
      "119": {
        "false": 21.47974967956543,
        "true": 19.08196449279785
      },
      "126": {
        "false": 18.795658111572266,
        "true": 47.73387145996094
      },
      "133": {
        "false": 19.969449996948242,
        "true": 48.48066711425781
      },
      "140": {
        "false": 55.97322082519531,
        "true": 49.1411247253418
      },
      "147": {
        "false": 55.34620666503906,
        "true": 47.6784782409668
      },
      "154": {
        "false": 55.159915924072266,
        "true": 46.65983581542969
      },
      "161": {
        "false": 56.67591857910156,
        "true": 47.563167572021484
      },
      "168": {
        "false": 58.783817291259766,
        "true": 47.987892150878906
      },
      "175": {
        "false": 58.52825164794922,
        "true": 47.391624450683594
      },
      "182": {
        "false": 55.40483093261719,
        "true": 45.825950622558594
      },
      "189": {
        "false": 50.16057205200195,
        "true": 39.09741973876953
      },
      "196": {
        "false": 53.1430549621582,
        "true": 41.63046646118164
      }
    }
  },
  {
    "experiment": "lstm_with_station_photo",
    "results": {
      "1": {
        "false": Infinity
      }
    }
  },
  {
    "experiment": "lstm_with_station_photo",
    "results": {
      "1": {
        "false": 12.79378890991211,
        "true": 13.326626777648926
      },
      "2": {
        "false": 13.059722900390625,
        "true": 13.00861644744873
      },
      "3": {
        "false": Infinity
      }
    }
  },
  {
    "experiment": "lstm_with_station_photo",
    "results": {
      "1": {
        "false": 42.97907257080078
      }
    }
  },
  {
    "experiment": "lstm_with_station_photo",
    "results": {
      "1": {
        "false": 43.337196350097656
      }
    }
  }
]